planhat/__init__.py
planhat/client.py
planhat-0.5.1.dist-info/WHEEL
planhat-0.5.1.dist-info/METADATA
planhat-0.5.1.dist-info/RECORD
